WeatherTracker/__init__.py
WeatherTracker/data/__init__.py
WeatherTracker/functions/__init__.py
WeatherTracker/functions/movmean.py
WeatherTracker/gui/__init__.py
WeatherTracker/gui/display.py
WeatherTracker/weather/__init__.py
WeatherTracker/weather/get_weather_data.py
WeatherTracker/weather/track_weather.py
WeatherTracker/weather/write_weather_data.py
WeatherTracker-0.0.1.dist-info/METADATA
WeatherTracker-0.0.1.dist-info/WHEEL
WeatherTracker-0.0.1.dist-info/top_level.txt
WeatherTracker-0.0.1.dist-info/RECORD
