Metadata-Version: 2.1
Name: WeatherTracker
Version: 0.0.1
Summary: Personal project for tracking weather
Home-page: https://github.com/bringel2/WeatherTracker
Author: Benjamin Ringel
Author-email: <benringel22@gmail.com>
License: UNKNOWN
Platform: UNKNOWN
Classifier: Programming Language :: Python :: 3
Classifier: License :: OSI Approved :: MIT License
Classifier: Operating System :: OS Independent
Requires-Python: >=3.7
